pyout/__init__.py
pyout/_version.py
pyout/common.py
pyout/elements.py
pyout/field.py
pyout/interface.py
pyout/summary.py
pyout/tabular.py
pyout/tabular_dummy.py
pyout/truncate.py
pyout/tests/__init__.py
pyout/tests/conftest.py
pyout/tests/tabular.py
pyout/tests/terminal.py
pyout/tests/test_elements.py
pyout/tests/test_field.py
pyout/tests/test_interface.py
pyout/tests/test_summary.py
pyout/tests/test_tabular.py
pyout/tests/test_tabular_dummy.py
pyout/tests/test_tests_utils.py
pyout/tests/test_truncate.py
pyout/tests/utils.py
pyout-0.8.0.dist-info/COPYING
pyout-0.8.0.dist-info/METADATA
pyout-0.8.0.dist-info/WHEEL
pyout-0.8.0.dist-info/top_level.txt
pyout-0.8.0.dist-info/RECORD
