Metadata-Version: 2.1
Name: pyout
Version: 0.8.0
Summary: Terminal styling for tabular data
Home-page: https://github.com/pyout/pyout.git
Author: Kyle Meyer
Author-email: kyle@kyleam.com
License: MIT
Keywords: terminal,tty,console,formatting,style,color
Classifier: Intended Audience :: Developers
Classifier: Natural Language :: English
Classifier: Environment :: Console
Classifier: Development Status :: 1 - Planning
Classifier: Topic :: Utilities
Classifier: Operating System :: POSIX
Classifier: Programming Language :: Python :: 3
Classifier: License :: OSI Approved :: MIT License
Classifier: Topic :: Software Development :: Libraries
Classifier: Topic :: Software Development :: User Interfaces
Classifier: Topic :: Terminals
Requires-Python: >=3.7
License-File: COPYING
Requires-Dist: blessed; sys_platform != "win32"
Requires-Dist: jsonschema>=3.0.0
